{
    "station":
    {
        "location": "Shefford, QC",
        "latitude": 45.2043,
        "longitude": -72.3529,
        "altitude (meters)": 300.0,
        "link": ""
    },
    "generation":
    {
        "time": "2024-09-03T17:00:00-0400",
        "generator": "weewx 5.1.0"
    },
    "current":
    {
        "temperature": {"value": 16.9207142857143, "units": "°C"},
        "humidity": {"value": 70.0, "units": "%"},
        "wind speed": {"value": 1.7935994451032065, "units": "km/h"},
        "wind gust": {"value": 2.6559991782973444, "units": "km/h"},
        "wind direction": {"value": 49.38662528542386, "units": "°"},
        "rain rate": {"value": 0.0, "units": "cm/h"},
        "void_end": null
    }
}