{
    "observations":[
    {
        "stationID": "Shefford, QC",
        "softwareType": "weewx 5.1.0",
        "realtimeFrequency": "5.0 minutes",
        "rainbool": false,
        "lon": -72.3529,
        "epoch": 1731603300,
        "lat": 45.2043,
        "winddir": 104.33902618319757,
        "humidity": 31.75,
        "imperial": {
                        "temp": 40.950050000000005,
                        "maxtemp": 41.199799999999996,
                        "mintemp": 25.7,
                        "apptemp": 33.519345956770444,
                        "dewpt": 13.202473067390379,
                        "windSpeed": 3.312883846843275,
                        "windGust": 4.222226439279507,
                        "precipRate": 0.0,
                        "rainday": 0.0
        },
        "metric": {
                        "temp": 4.9722500000000025,
                        "maxtemp": 5.110999999999998,
                        "mintemp": -3.5000000000000004,
                        "apptemp": 0.8440810870946909,
                        "dewpt": -10.443070518116455,
                        "windSpeed": 5.331556490078756,
                        "windGust": 6.794997897790081,
                        "precipRate": 0.0,
                        "rainday": 0.0
        },
        "metric_si": {
                        "temp": 4.9722500000000025,
                        "maxtemp": 5.110999999999998,
                        "mintemp": -3.5000000000000004,
                        "apptemp": 0.8440810870946909,
                        "dewpt": -10.443070518116455,
                        "windSpeed": 1.4809879150955558,
                        "windGust": 1.8874994175627997,
                        "precipRate": 0.0,
                        "rainday": 0.0
        },
        "uk_hybrid": {
                        "temp": 4.9722500000000025,
                        "maxtemp": 5.110999999999998,
                        "mintemp": -3.5000000000000004,
                        "apptemp": 0.8440810870946909,
                        "dewpt": -10.443070518116455,
                        "windSpeed": 3.312883846843275,
                        "windGust": 4.222226439279507,
                        "precipRate": 0.0,
                        "rainday": 0.0
        }
    }
    ]
}
