{
    "observations":[
    {
        "stationID": "Shefford, QC",
        "softwareType": "weewx 5.1.0",
        "realtimeFrequency": "5.0 minutes",
        "rainbool": false,
        "lon": -72.3529,
        "epoch": 1730509200,
        "lat": 45.2043,
        "winddir": 90.0,
        "humidity": 85.63157894736842,
        "imperial": {
                        "temp": 38.83194736842103,
                        "maxtemp": 68.19980000000001,
                        "mintemp": 38.800399999999996,
                        "apptemp": 35.60463351730104,
                        "dewpt": 34.90081098681615,
                        "windSpeed": 0.1943884527309339,
                        "windGust": 1.650365477958259,
                        "precipRate": 0.0,
                        "rainday": 0.28000000000000114
        },
        "metric": {
                        "temp": 3.795526315789459,
                        "maxtemp": 20.111000000000004,
                        "mintemp": 3.777999999999998,
                        "apptemp": 2.002574176278355,
                        "dewpt": 1.6115616593423039,
                        "windSpeed": 0.31283711251800117,
                        "windGust": 2.6559991782973444,
                        "precipRate": 0.0,
                        "rainday": 7.112000000000029
        },
        "metric_si": {
                        "temp": 3.795526315789459,
                        "maxtemp": 20.111000000000004,
                        "mintemp": 3.777999999999998,
                        "apptemp": 2.002574176278355,
                        "dewpt": 1.6115616593423039,
                        "windSpeed": 0.08689919799118634,
                        "windGust": 0.7377775501172621,
                        "precipRate": 0.0,
                        "rainday": 7.112000000000029
        },
        "uk_hybrid": {
                        "temp": 3.795526315789459,
                        "maxtemp": 20.111000000000004,
                        "mintemp": 3.777999999999998,
                        "apptemp": 2.002574176278355,
                        "dewpt": 1.6115616593423039,
                        "windSpeed": 0.1943884527309339,
                        "windGust": 1.650365477958259,
                        "precipRate": 0.0,
                        "rainday": 7.112000000000029
        }
    }
    ]
}
