{
    "observations":[
    {
        "stationID": "Shefford, QC",
        "softwareType": "weewx 5.1.0",
        "realtimeFrequency": "5.0 minutes",
        "rainbool": false,
        "lon": -72.3529,
        "epoch": 1730962500,
        "lat": 45.2043,
        "winddir": 153.81046120363402,
        "humidity": 96.125,
        "imperial": {
                        "temp": 43.92477500000002,
                        "maxtemp": 46.7996,
                        "mintemp": 43.8998,
                        "apptemp": 41.48683005290679,
                        "dewpt": 42.892639020068636,
                        "windSpeed": 1.4880319007306255,
                        "windGust": 2.6787370389601106,
                        "precipRate": 0.0,
                        "rainday": 0.0
        },
        "metric": {
                        "temp": 6.62487500000001,
                        "maxtemp": 8.222,
                        "mintemp": 6.610999999999999,
                        "apptemp": 5.270461140503772,
                        "dewpt": 6.0514661222603525,
                        "windSpeed": 2.394749259121825,
                        "windGust": 4.310998666280064,
                        "precipRate": 0.0,
                        "rainday": 0.0
        },
        "metric_si": {
                        "temp": 6.62487500000001,
                        "maxtemp": 8.222,
                        "mintemp": 6.610999999999999,
                        "apptemp": 5.270461140503772,
                        "dewpt": 6.0514661222603525,
                        "windSpeed": 0.6652081280660067,
                        "windGust": 1.1974996304802394,
                        "precipRate": 0.0,
                        "rainday": 0.0
        },
        "uk_hybrid": {
                        "temp": 6.62487500000001,
                        "maxtemp": 8.222,
                        "mintemp": 6.610999999999999,
                        "apptemp": 5.270461140503772,
                        "dewpt": 6.0514661222603525,
                        "windSpeed": 1.4880319007306255,
                        "windGust": 2.6787370389601106,
                        "precipRate": 0.0,
                        "rainday": 0.0
        }
    }
    ]
}
