{
    "observations":[
    {
        "stationID": "Shefford, QC",
        "softwareType": "weewx 5.1.0",
        "realtimeFrequency": "5.0 minutes",
        "rainbool": false,
        "lon": -72.3529,
        "epoch": 1724689200,
        "lat": 45.2043,
        "winddir": 129.38042584996225,
        "humidity": 77.6086956521739,
        "imperial": {
                        "temp": 73.05643478260869,
                        "maxtemp": 78.9998,
                        "mintemp": 61.7,
                        "apptemp": 78.25669576815083,
                        "dewpt": 65.62502269736154,
                        "windSpeed": 0.6474123891801442,
                        "windGust": 2.6787370389601106,
                        "precipRate": 0.0,
                        "rainday": 0.0
        },
        "metric": {
                        "temp": 22.809130434782606,
                        "maxtemp": 26.110999999999997,
                        "mintemp": 16.5,
                        "apptemp": 25.698164315639353,
                        "dewpt": 18.680568165200857,
                        "windSpeed": 1.0419066544031732,
                        "windGust": 4.310998666280064,
                        "precipRate": 0.0,
                        "rainday": 0.0
        },
        "metric_si": {
                        "temp": 22.809130434782606,
                        "maxtemp": 26.110999999999997,
                        "mintemp": 16.5,
                        "apptemp": 25.698164315639353,
                        "dewpt": 18.680568165200857,
                        "windSpeed": 0.28941851534352736,
                        "windGust": 1.1974996304802394,
                        "precipRate": 0.0,
                        "rainday": 0.0
        },
        "uk_hybrid": {
                        "temp": 22.809130434782606,
                        "maxtemp": 26.110999999999997,
                        "mintemp": 16.5,
                        "apptemp": 25.698164315639353,
                        "dewpt": 18.680568165200857,
                        "windSpeed": 0.6474123891801442,
                        "windGust": 2.6787370389601106,
                        "precipRate": 0.0,
                        "rainday": 0.0
        }
    }
    ]
}
