{
    "observations":[
    {
        "stationID": "Shefford, QC",
        "softwareType": "weewx 5.1.0",
        "realtimeFrequency": "5.0 minutes",
        "rainbool": false,
        "lon": -72.3529,
        "epoch": 1732207200,
        "lat": 45.2043,
        "winddir": 143.41662258587473,
        "humidity": 84.0,
        "imperial": {
                        "temp": 43.89980000000001,
                        "maxtemp": 43.89980000000002,
                        "mintemp": 38.4998,
                        "apptemp": 39.52050427876964,
                        "dewpt": 39.38348556842462,
                        "windSpeed": 3.5238924668667693,
                        "windGust": 5.250598000281358,
                        "precipRate": 0.0,
                        "rainday": 0.0
        },
        "metric": {
                        "temp": 6.611000000000007,
                        "maxtemp": 6.611000000000011,
                        "mintemp": 3.611,
                        "apptemp": 4.178057932649802,
                        "dewpt": 4.101936426902565,
                        "windSpeed": 5.671141102627367,
                        "windGust": 8.4499973857728,
                        "precipRate": 0.0,
                        "rainday": 0.0
        },
        "metric_si": {
                        "temp": 6.611000000000007,
                        "maxtemp": 6.611000000000011,
                        "mintemp": 3.611,
                        "apptemp": 4.178057932649802,
                        "dewpt": 4.101936426902565,
                        "windSpeed": 1.5753169742122997,
                        "windGust": 2.347221497925777,
                        "precipRate": 0.0,
                        "rainday": 0.0
        },
        "uk_hybrid": {
                        "temp": 6.611000000000007,
                        "maxtemp": 6.611000000000011,
                        "mintemp": 3.611,
                        "apptemp": 4.178057932649802,
                        "dewpt": 4.101936426902565,
                        "windSpeed": 3.5238924668667693,
                        "windGust": 5.250598000281358,
                        "precipRate": 0.0,
                        "rainday": 0.0
        }
    }
    ]
}
