{
    "observations":[
    {
        "stationID": "Shefford, QC",
        "softwareType": "weewx 5.1.0",
        "realtimeFrequency": "5.0 minutes",
        "rainbool": false,
        "lon": -72.3529,
        "epoch": 1725927000,
        "lat": 45.2043,
        "winddir": 95.27085241746484,
        "humidity": 91.375,
        "imperial": {
                        "temp": 56.125175000000006,
                        "maxtemp": 68.7002,
                        "mintemp": 46.2002,
                        "apptemp": 56.782628780082945,
                        "dewpt": 53.64476147553649,
                        "windSpeed": 0.8706982778573081,
                        "windGust": 1.650365477958259,
                        "precipRate": 0.0,
                        "rainday": 0.0
        },
        "metric": {
                        "temp": 13.402875000000003,
                        "maxtemp": 20.388999999999996,
                        "mintemp": 7.889000000000001,
                        "apptemp": 13.76812710004608,
                        "dewpt": 12.02486748640916,
                        "windSpeed": 1.4012495664868803,
                        "windGust": 2.6559991782973444,
                        "precipRate": 0.0,
                        "rainday": 0.0
        },
        "metric_si": {
                        "temp": 13.402875000000003,
                        "maxtemp": 20.388999999999996,
                        "mintemp": 7.889000000000001,
                        "apptemp": 13.76812710004608,
                        "dewpt": 12.02486748640916,
                        "windSpeed": 0.3892359910021888,
                        "windGust": 0.7377775501172621,
                        "precipRate": 0.0,
                        "rainday": 0.0
        },
        "uk_hybrid": {
                        "temp": 13.402875000000003,
                        "maxtemp": 20.388999999999996,
                        "mintemp": 7.889000000000001,
                        "apptemp": 13.76812710004608,
                        "dewpt": 12.02486748640916,
                        "windSpeed": 0.8706982778573081,
                        "windGust": 1.650365477958259,
                        "precipRate": 0.0,
                        "rainday": 0.0
        }
    }
    ]
}
