{
    "observations":[
    {
        "stationID": "Shefford, QC",
        "softwareType": "weewx 5.1.0",
        "realtimeFrequency": "5.0 minutes",
        "rainbool": false,
        "lon": -72.3529,
        "epoch": 1723680600,
        "lat": 45.2043,
        "winddir": 18.536590309101527,
        "humidity": 78.71428571428571,
        "imperial": {
                        "temp": 69.40039999999999,
                        "maxtemp": 80.6,
                        "mintemp": 61.50019999999998,
                        "apptemp": 72.83541433165263,
                        "dewpt": 62.492387071708905,
                        "windSpeed": 1.45892493218221,
                        "windGust": 1.650365477958259,
                        "precipRate": 0.0,
                        "rainday": 0.0
        },
        "metric": {
                        "temp": 20.777999999999995,
                        "maxtemp": 26.999999999999996,
                        "mintemp": 16.388999999999985,
                        "apptemp": 22.68634129536257,
                        "dewpt": 16.94021503983828,
                        "windSpeed": 2.347906250358118,
                        "windGust": 2.6559991782973444,
                        "precipRate": 0.0,
                        "rainday": 0.0
        },
        "metric_si": {
                        "temp": 20.777999999999995,
                        "maxtemp": 26.999999999999996,
                        "mintemp": 16.388999999999985,
                        "apptemp": 22.68634129536257,
                        "dewpt": 16.94021503983828,
                        "windSpeed": 0.6521961811767896,
                        "windGust": 0.7377775501172621,
                        "precipRate": 0.0,
                        "rainday": 0.0
        },
        "uk_hybrid": {
                        "temp": 20.777999999999995,
                        "maxtemp": 26.999999999999996,
                        "mintemp": 16.388999999999985,
                        "apptemp": 22.68634129536257,
                        "dewpt": 16.94021503983828,
                        "windSpeed": 1.45892493218221,
                        "windGust": 1.650365477958259,
                        "precipRate": 0.0,
                        "rainday": 0.0
        }
    }
    ]
}
