{
    "observations":[
    {
        "stationID": "Shefford, QC",
        "softwareType": "weewx 5.1.0",
        "realtimeFrequency": "5.0 minutes",
        "rainbool": false,
        "lon": -72.3529,
        "epoch": 1730028000,
        "lat": 45.2043,
        "winddir": 271.68135686466576,
        "humidity": 77.125,
        "imperial": {
                        "temp": 31.600400000000008,
                        "maxtemp": 33.6002,
                        "mintemp": 28.799599999999998,
                        "apptemp": 26.11439377512596,
                        "dewpt": 25.271346318903266,
                        "windSpeed": 1.7720379893109328,
                        "windGust": 3.1932335057332426,
                        "precipRate": 0.0,
                        "rainday": 0.0
        },
        "metric": {
                        "temp": -0.22199999999999578,
                        "maxtemp": 0.8890000000000005,
                        "mintemp": -1.778000000000001,
                        "apptemp": -3.2697812360411325,
                        "dewpt": -3.73814093394263,
                        "windSpeed": 2.8518116177176567,
                        "windGust": 5.138998410116736,
                        "precipRate": 0.0,
                        "rainday": 0.0
        },
        "metric_si": {
                        "temp": -0.22199999999999578,
                        "maxtemp": 0.8890000000000005,
                        "mintemp": -1.778000000000001,
                        "apptemp": -3.2697812360411325,
                        "dewpt": -3.73814093394263,
                        "windSpeed": 0.792169894444196,
                        "windGust": 1.4274995595077595,
                        "precipRate": 0.0,
                        "rainday": 0.0
        },
        "uk_hybrid": {
                        "temp": -0.22199999999999578,
                        "maxtemp": 0.8890000000000005,
                        "mintemp": -1.778000000000001,
                        "apptemp": -3.2697812360411325,
                        "dewpt": -3.73814093394263,
                        "windSpeed": 1.7720379893109328,
                        "windGust": 3.1932335057332426,
                        "precipRate": 0.0,
                        "rainday": 0.0
        }
    }
    ]
}
