{
    "observations":[
    {
        "stationID": "Shefford, QC",
        "softwareType": "weewx 5.1.0",
        "realtimeFrequency": "5.0 minutes",
        "rainbool": false,
        "lon": -72.3529,
        "epoch": 1729171200,
        "lat": 45.2043,
        "winddir": 292.7224048984241,
        "humidity": 90.0,
        "imperial": {
                        "temp": 39.599825,
                        "maxtemp": 39.7004,
                        "mintemp": 34.300399999999996,
                        "apptemp": 35.19409166064156,
                        "dewpt": 36.912675640392756,
                        "windSpeed": 2.7752051264800714,
                        "windGust": 3.7077299725063737,
                        "precipRate": 0.0,
                        "rainday": 0.0
        },
        "metric": {
                        "temp": 4.222125000000001,
                        "maxtemp": 4.278000000000001,
                        "mintemp": 1.2779999999999978,
                        "apptemp": 1.7744953670230896,
                        "dewpt": 2.7292642446626423,
                        "windSpeed": 4.466248618249438,
                        "windGust": 5.966998153953408,
                        "precipRate": 0.0,
                        "rainday": 0.0
        },
        "metric_si": {
                        "temp": 4.222125000000001,
                        "maxtemp": 4.278000000000001,
                        "mintemp": 1.2779999999999978,
                        "apptemp": 1.7744953670230896,
                        "dewpt": 2.7292642446626423,
                        "windSpeed": 1.240624617172899,
                        "windGust": 1.6574994885352794,
                        "precipRate": 0.0,
                        "rainday": 0.0
        },
        "uk_hybrid": {
                        "temp": 4.222125000000001,
                        "maxtemp": 4.278000000000001,
                        "mintemp": 1.2779999999999978,
                        "apptemp": 1.7744953670230896,
                        "dewpt": 2.7292642446626423,
                        "windSpeed": 2.7752051264800714,
                        "windGust": 3.7077299725063737,
                        "precipRate": 0.0,
                        "rainday": 0.0
        }
    }
    ]
}
