{
    "observations":[
    {
        "stationID": "Shefford, QC",
        "softwareType": "weewx 5.1.0",
        "realtimeFrequency": "5.0 minutes",
        "rainbool": false,
        "lon": -72.3529,
        "epoch": 1731264000,
        "lat": 45.2043,
        "winddir": 294.24958628841193,
        "humidity": 33.40909090909091,
        "imperial": {
                        "temp": 49.381536363636364,
                        "maxtemp": 53.799800000000005,
                        "mintemp": 29.299999999999994,
                        "apptemp": 42.77371577974957,
                        "dewpt": 21.788733750092668,
                        "windSpeed": 3.2491165104339474,
                        "windGust": 4.736101533508226,
                        "precipRate": 0.0,
                        "rainday": 0.0
        },
        "metric": {
                        "temp": 9.656409090909092,
                        "maxtemp": 12.111000000000002,
                        "mintemp": -1.5000000000000036,
                        "apptemp": 5.985397655416429,
                        "dewpt": -5.672925694392962,
                        "windSpeed": 5.228933164901768,
                        "windGust": 7.621997641936128,
                        "precipRate": 0.0,
                        "rainday": 0.0
        },
        "metric_si": {
                        "temp": 9.656409090909092,
                        "maxtemp": 12.111000000000002,
                        "mintemp": -1.5000000000000036,
                        "apptemp": 5.985397655416429,
                        "dewpt": -5.672925694392962,
                        "windSpeed": 1.4524814358569207,
                        "windGust": 2.117221568898257,
                        "precipRate": 0.0,
                        "rainday": 0.0
        },
        "uk_hybrid": {
                        "temp": 9.656409090909092,
                        "maxtemp": 12.111000000000002,
                        "mintemp": -1.5000000000000036,
                        "apptemp": 5.985397655416429,
                        "dewpt": -5.672925694392962,
                        "windSpeed": 3.2491165104339474,
                        "windGust": 4.736101533508226,
                        "precipRate": 0.0,
                        "rainday": 0.0
        }
    }
    ]
}
