{
    "observations":[
    {
        "stationID": "Shefford, QC",
        "softwareType": "weewx 5.1.0",
        "realtimeFrequency": "5.0 minutes",
        "rainbool": false,
        "lon": -72.3529,
        "epoch": 1735716600,
        "lat": 45.2043,
        "winddir": 123.84526681829773,
        "humidity": 86.0,
        "imperial": {
                        "temp": 35.400200000000005,
                        "maxtemp": 36.5,
                        "mintemp": 35.0996,
                        "apptemp": 29.323275548798815,
                        "dewpt": 31.637099770569886,
                        "windSpeed": 4.495498151896443,
                        "windGust": 5.250598000281358,
                        "precipRate": 0.0,
                        "rainday": 0.0
        },
        "metric": {
                        "temp": 1.889000000000003,
                        "maxtemp": 2.5,
                        "mintemp": 1.7220000000000013,
                        "apptemp": -1.487069139556214,
                        "dewpt": -0.20161123857228544,
                        "windSpeed": 7.234784995773023,
                        "windGust": 8.4499973857728,
                        "precipRate": 0.0,
                        "rainday": 0.0
        },
        "metric_si": {
                        "temp": 1.889000000000003,
                        "maxtemp": 2.5,
                        "mintemp": 1.7220000000000013,
                        "apptemp": -1.487069139556214,
                        "dewpt": -0.20161123857228544,
                        "windSpeed": 2.0096625004335693,
                        "windGust": 2.347221497925777,
                        "precipRate": 0.0,
                        "rainday": 0.0
        },
        "uk_hybrid": {
                        "temp": 1.889000000000003,
                        "maxtemp": 2.5,
                        "mintemp": 1.7220000000000013,
                        "apptemp": -1.487069139556214,
                        "dewpt": -0.20161123857228544,
                        "windSpeed": 4.495498151896443,
                        "windGust": 5.250598000281358,
                        "precipRate": 0.0,
                        "rainday": 0.0
        }
    }
    ]
}
