{
    "observations":[
    {
        "stationID": "Shefford, QC",
        "softwareType": "weewx 5.1.0",
        "realtimeFrequency": "5.0 minutes",
        "rainbool": true,
        "lon": -72.3529,
        "epoch": 1727350500,
        "lat": 45.2043,
        "winddir": 4.802319630557008,
        "humidity": 99.0,
        "imperial": {
                        "temp": 53.87472500000002,
                        "maxtemp": 53.9996,
                        "mintemp": 53.599999999999994,
                        "apptemp": 54.40985106558107,
                        "dewpt": 53.599787591707354,
                        "windSpeed": 0.8083912297557169,
                        "windGust": 2.164240572186979,
                        "precipRate": 0.06893617014245473,
                        "rainday": 0.410000000000002
        },
        "metric": {
                        "temp": 12.152625000000011,
                        "maxtemp": 12.222,
                        "mintemp": 11.999999999999996,
                        "apptemp": 12.449917258656152,
                        "dewpt": 11.999881995392974,
                        "windSpeed": 1.3009763416950653,
                        "windGust": 3.4829989224433926,
                        "precipRate": 1.7509787234043486,
                        "rainday": 10.41400000000005
        },
        "metric_si": {
                        "temp": 12.152625000000011,
                        "maxtemp": 12.222,
                        "mintemp": 11.999999999999996,
                        "apptemp": 12.449917258656152,
                        "dewpt": 11.999881995392974,
                        "windSpeed": 0.36138231742662397,
                        "windGust": 0.9674997014527198,
                        "precipRate": 1.7509787234043486,
                        "rainday": 10.41400000000005
        },
        "uk_hybrid": {
                        "temp": 12.152625000000011,
                        "maxtemp": 12.222,
                        "mintemp": 11.999999999999996,
                        "apptemp": 12.449917258656152,
                        "dewpt": 11.999881995392974,
                        "windSpeed": 0.8083912297557169,
                        "windGust": 2.164240572186979,
                        "precipRate": 1.7509787234043486,
                        "rainday": 10.41400000000005
        }
    }
    ]
}
