{
    "observations":[
    {
        "stationID": "Shefford, QC",
        "softwareType": "weewx 5.1.0",
        "realtimeFrequency": "5.0 minutes",
        "rainbool": false,
        "lon": -72.3529,
        "epoch": 1726913100,
        "lat": 45.2043,
        "winddir": 128.81235823778238,
        "humidity": 87.0,
        "imperial": {
                        "temp": 58.53740000000002,
                        "maxtemp": 61.199600000000004,
                        "mintemp": 58.4996,
                        "apptemp": 59.36271790840198,
                        "dewpt": 54.679001778418176,
                        "windSpeed": 1.1090723202073602,
                        "windGust": 2.164240572186979,
                        "precipRate": 0.0,
                        "rainday": 0.0
        },
        "metric": {
                        "temp": 14.743000000000011,
                        "maxtemp": 16.222,
                        "mintemp": 14.722,
                        "apptemp": 15.201509949112213,
                        "dewpt": 12.59944543245454,
                        "windSpeed": 1.784874447802513,
                        "windGust": 3.4829989224433926,
                        "precipRate": 0.0,
                        "rainday": 0.0
        },
        "metric_si": {
                        "temp": 14.743000000000011,
                        "maxtemp": 16.222,
                        "mintemp": 14.722,
                        "apptemp": 15.201509949112213,
                        "dewpt": 12.59944543245454,
                        "windSpeed": 0.49579845811955897,
                        "windGust": 0.9674997014527198,
                        "precipRate": 0.0,
                        "rainday": 0.0
        },
        "uk_hybrid": {
                        "temp": 14.743000000000011,
                        "maxtemp": 16.222,
                        "mintemp": 14.722,
                        "apptemp": 15.201509949112213,
                        "dewpt": 12.59944543245454,
                        "windSpeed": 1.1090723202073602,
                        "windGust": 2.164240572186979,
                        "precipRate": 0.0,
                        "rainday": 0.0
        }
    }
    ]
}
