{
    "observations":[
    {
        "stationID": "Shefford, QC",
        "softwareType": "weewx 5.1.0",
        "realtimeFrequency": "5.0 minutes",
        "rainbool": true,
        "lon": -72.3529,
        "epoch": 1735428300,
        "lat": 45.2043,
        "winddir": 305.7290930669933,
        "humidity": 99.0,
        "imperial": {
                        "temp": 35.863372727272726,
                        "maxtemp": 37.5998,
                        "mintemp": 14.3996,
                        "apptemp": 31.97451412837484,
                        "dewpt": 35.61000998753534,
                        "windSpeed": 1.4926719326655278,
                        "windGust": 2.164240572186979,
                        "precipRate": 0.2643999997303093,
                        "rainday": 0.43999999999999767
        },
        "metric": {
                        "temp": 2.146318181818181,
                        "maxtemp": 3.111000000000001,
                        "mintemp": -9.778,
                        "apptemp": -0.014158817569533966,
                        "dewpt": 2.005561104186301,
                        "windSpeed": 2.40221664811594,
                        "windGust": 3.4829989224433926,
                        "precipRate": 6.715759999999932,
                        "rainday": 11.175999999999942
        },
        "metric_si": {
                        "temp": 2.146318181818181,
                        "maxtemp": 3.111000000000001,
                        "mintemp": -9.778,
                        "apptemp": -0.014158817569533966,
                        "dewpt": 2.005561104186301,
                        "windSpeed": 0.6672824027882537,
                        "windGust": 0.9674997014527198,
                        "precipRate": 6.715759999999932,
                        "rainday": 11.175999999999942
        },
        "uk_hybrid": {
                        "temp": 2.146318181818181,
                        "maxtemp": 3.111000000000001,
                        "mintemp": -9.778,
                        "apptemp": -0.014158817569533966,
                        "dewpt": 2.005561104186301,
                        "windSpeed": 1.4926719326655278,
                        "windGust": 2.164240572186979,
                        "precipRate": 6.715759999999932,
                        "rainday": 11.175999999999942
        }
    }
    ]
}
