{
    "observations":[
    {
        "stationID": "Shefford, QC",
        "softwareType": "weewx 5.1.0",
        "realtimeFrequency": "5.0 minutes",
        "rainbool": false,
        "lon": -72.3529,
        "epoch": 1724420400,
        "lat": 45.2043,
        "winddir": 281.25,
        "humidity": 97.25,
        "imperial": {
                        "temp": 60.17495000000002,
                        "maxtemp": 61.7,
                        "mintemp": 54.30019999999999,
                        "apptemp": 62.680931648190096,
                        "dewpt": 59.391137647108444,
                        "windSpeed": 0.887278568584035,
                        "windGust": 2.6787370389601106,
                        "precipRate": 0.0,
                        "rainday": 0.0
        },
        "metric": {
                        "temp": 15.652750000000008,
                        "maxtemp": 16.5,
                        "mintemp": 12.388999999999994,
                        "apptemp": 17.044962026772275,
                        "dewpt": 15.217298692838025,
                        "windSpeed": 1.427932891565031,
                        "windGust": 4.310998666280064,
                        "precipRate": 0.0,
                        "rainday": 0.0
        },
        "metric_si": {
                        "temp": 15.652750000000008,
                        "maxtemp": 16.5,
                        "mintemp": 12.388999999999994,
                        "apptemp": 17.044962026772275,
                        "dewpt": 15.217298692838025,
                        "windSpeed": 0.3966480257520492,
                        "windGust": 1.1974996304802394,
                        "precipRate": 0.0,
                        "rainday": 0.0
        },
        "uk_hybrid": {
                        "temp": 15.652750000000008,
                        "maxtemp": 16.5,
                        "mintemp": 12.388999999999994,
                        "apptemp": 17.044962026772275,
                        "dewpt": 15.217298692838025,
                        "windSpeed": 0.887278568584035,
                        "windGust": 2.6787370389601106,
                        "precipRate": 0.0,
                        "rainday": 0.0
        }
    }
    ]
}
