{
    "observations":[
    {
        "stationID": "Shefford, QC",
        "softwareType": "weewx 5.1.0",
        "realtimeFrequency": "5.0 minutes",
        "rainbool": false,
        "lon": -72.3529,
        "epoch": 1724951700,
        "lat": 45.2043,
        "winddir": 211.9650083148806,
        "humidity": 46.25,
        "imperial": {
                        "temp": 70.21265000000001,
                        "maxtemp": 76.4996,
                        "mintemp": 49.299800000000005,
                        "apptemp": 68.31078168539683,
                        "dewpt": 48.59070134849236,
                        "windSpeed": 2.7012685477444416,
                        "windGust": 5.76509446705449,
                        "precipRate": 0.0,
                        "rainday": 0.0
        },
        "metric": {
                        "temp": 21.229250000000004,
                        "maxtemp": 24.722,
                        "mintemp": 9.611000000000002,
                        "apptemp": 20.17265649188713,
                        "dewpt": 9.217056304717977,
                        "windSpeed": 4.34725952462704,
                        "windGust": 9.277997129609473,
                        "precipRate": 0.0,
                        "rainday": 0.0
        },
        "metric_si": {
                        "temp": 21.229250000000004,
                        "maxtemp": 24.722,
                        "mintemp": 9.611000000000002,
                        "apptemp": 20.17265649188713,
                        "dewpt": 9.217056304717977,
                        "windSpeed": 1.2075720911402352,
                        "windGust": 2.577221426953297,
                        "precipRate": 0.0,
                        "rainday": 0.0
        },
        "uk_hybrid": {
                        "temp": 21.229250000000004,
                        "maxtemp": 24.722,
                        "mintemp": 9.611000000000002,
                        "apptemp": 20.17265649188713,
                        "dewpt": 9.217056304717977,
                        "windSpeed": 2.7012685477444416,
                        "windGust": 5.76509446705449,
                        "precipRate": 0.0,
                        "rainday": 0.0
        }
    }
    ]
}
