{
    "observations":[
    {
        "stationID": "Shefford, QC",
        "softwareType": "weewx 5.1.0",
        "realtimeFrequency": "5.0 minutes",
        "rainbool": false,
        "lon": -72.3529,
        "epoch": 1734714000,
        "lat": 45.2043,
        "humidity": 86.04545454545455,
        "imperial": {
                        "temp": 22.05459090909091,
                        "maxtemp": 22.299799999999998,
                        "mintemp": 11.6996,
                        "apptemp": 16.923391699719772,
                        "dewpt": 18.532033641512882,
                        "windSpeed": 0.0,
                        "windGust": 0.0,
                        "precipRate": 0.0,
                        "rainday": 0.0
        },
        "metric": {
                        "temp": -5.525227272727273,
                        "maxtemp": -5.389000000000001,
                        "mintemp": -11.278,
                        "apptemp": -8.375893500155682,
                        "dewpt": -7.482203532492843,
                        "windSpeed": 0.0,
                        "windGust": 0.0,
                        "precipRate": 0.0,
                        "rainday": 0.0
        },
        "metric_si": {
                        "temp": -5.525227272727273,
                        "maxtemp": -5.389000000000001,
                        "mintemp": -11.278,
                        "apptemp": -8.375893500155682,
                        "dewpt": -7.482203532492843,
                        "windSpeed": 0.0,
                        "windGust": 0.0,
                        "precipRate": 0.0,
                        "rainday": 0.0
        },
        "uk_hybrid": {
                        "temp": -5.525227272727273,
                        "maxtemp": -5.389000000000001,
                        "mintemp": -11.278,
                        "apptemp": -8.375893500155682,
                        "dewpt": -7.482203532492843,
                        "windSpeed": 0.0,
                        "windGust": 0.0,
                        "precipRate": 0.0,
                        "rainday": 0.0
        }
    }
    ]
}
