{
    "observations":[
    {
        "stationID": "Shefford, QC",
        "softwareType": "weewx 5.1.0",
        "realtimeFrequency": "5.0 minutes",
        "rainbool": false,
        "lon": -72.3529,
        "epoch": 1728164400,
        "lat": 45.2043,
        "winddir": 207.3886959202622,
        "humidity": 69.25,
        "imperial": {
                        "temp": 55.000399999999985,
                        "maxtemp": 68.0,
                        "mintemp": 48.2,
                        "apptemp": 52.721772886825185,
                        "dewpt": 45.113156474366654,
                        "windSpeed": 2.382847200467925,
                        "windGust": 3.7077299725063737,
                        "precipRate": 0.0,
                        "rainday": 0.009999999999999787
        },
        "metric": {
                        "temp": 12.777999999999992,
                        "maxtemp": 20.0,
                        "mintemp": 9.000000000000002,
                        "apptemp": 11.512096048236215,
                        "dewpt": 7.285086930203697,
                        "windSpeed": 3.8348113136010498,
                        "windGust": 5.966998153953408,
                        "precipRate": 0.0,
                        "rainday": 0.25399999999999456
        },
        "metric_si": {
                        "temp": 12.777999999999992,
                        "maxtemp": 20.0,
                        "mintemp": 9.000000000000002,
                        "apptemp": 11.512096048236215,
                        "dewpt": 7.285086930203697,
                        "windSpeed": 1.0652253657413606,
                        "windGust": 1.6574994885352794,
                        "precipRate": 0.0,
                        "rainday": 0.25399999999999456
        },
        "uk_hybrid": {
                        "temp": 12.777999999999992,
                        "maxtemp": 20.0,
                        "mintemp": 9.000000000000002,
                        "apptemp": 11.512096048236215,
                        "dewpt": 7.285086930203697,
                        "windSpeed": 2.382847200467925,
                        "windGust": 3.7077299725063737,
                        "precipRate": 0.0,
                        "rainday": 0.25399999999999456
        }
    }
    ]
}
