{
    "observations":[
    {
        "stationID": "Shefford, QC",
        "softwareType": "weewx 5.1.0",
        "realtimeFrequency": "5.0 minutes",
        "rainbool": false,
        "lon": -72.3529,
        "epoch": 1731288300,
        "lat": 45.2043,
        "winddir": 15.572731391746558,
        "humidity": 67.68181818181819,
        "imperial": {
                        "temp": 41.663872727272725,
                        "maxtemp": 53.799800000000005,
                        "mintemp": 29.299999999999994,
                        "apptemp": 36.43083540823673,
                        "dewpt": 31.774669488274466,
                        "windSpeed": 2.8465076259513484,
                        "windGust": 4.222226439279507,
                        "precipRate": 0.0,
                        "rainday": 0.010000000000001563
        },
        "metric": {
                        "temp": 5.36881818181818,
                        "maxtemp": 12.111000000000002,
                        "mintemp": -1.5000000000000036,
                        "apptemp": 2.461575226798184,
                        "dewpt": -0.1251836176252969,
                        "windSpeed": 4.580998582748543,
                        "windGust": 6.794997897790081,
                        "precipRate": 0.0,
                        "rainday": 0.2540000000000397
        },
        "metric_si": {
                        "temp": 5.36881818181818,
                        "maxtemp": 12.111000000000002,
                        "mintemp": -1.5000000000000036,
                        "apptemp": 2.461575226798184,
                        "dewpt": -0.1251836176252969,
                        "windSpeed": 1.2724996073370392,
                        "windGust": 1.8874994175627997,
                        "precipRate": 0.0,
                        "rainday": 0.2540000000000397
        },
        "uk_hybrid": {
                        "temp": 5.36881818181818,
                        "maxtemp": 12.111000000000002,
                        "mintemp": -1.5000000000000036,
                        "apptemp": 2.461575226798184,
                        "dewpt": -0.1251836176252969,
                        "windSpeed": 2.8465076259513484,
                        "windGust": 4.222226439279507,
                        "precipRate": 0.0,
                        "rainday": 0.2540000000000397
        }
    }
    ]
}
