{
    "observations":[
    {
        "stationID": "Shefford, QC",
        "softwareType": "weewx 5.1.0",
        "realtimeFrequency": "5.0 minutes",
        "rainbool": false,
        "lon": -72.3529,
        "epoch": 1725552000,
        "lat": 45.2043,
        "winddir": 318.76782951812004,
        "humidity": 52.36363636363637,
        "imperial": {
                        "temp": 75.50886363636364,
                        "maxtemp": 76.80019999999999,
                        "mintemp": 59.399599999999985,
                        "apptemp": 76.82094300336843,
                        "dewpt": 56.821948421610266,
                        "windSpeed": 1.504883253973103,
                        "windGust": 2.164240572186979,
                        "precipRate": 0.0,
                        "rainday": 0.0
        },
        "metric": {
                        "temp": 24.171590909090913,
                        "maxtemp": 24.888999999999992,
                        "mintemp": 15.22199999999999,
                        "apptemp": 24.900523890760237,
                        "dewpt": 13.789971345339037,
                        "windSpeed": 2.4218688159490736,
                        "windGust": 3.4829989224433926,
                        "precipRate": 0.0,
                        "rainday": 0.0
        },
        "metric_si": {
                        "temp": 24.171590909090913,
                        "maxtemp": 24.888999999999992,
                        "mintemp": 15.22199999999999,
                        "apptemp": 24.900523890760237,
                        "dewpt": 13.789971345339037,
                        "windSpeed": 0.6727413383018246,
                        "windGust": 0.9674997014527198,
                        "precipRate": 0.0,
                        "rainday": 0.0
        },
        "uk_hybrid": {
                        "temp": 24.171590909090913,
                        "maxtemp": 24.888999999999992,
                        "mintemp": 15.22199999999999,
                        "apptemp": 24.900523890760237,
                        "dewpt": 13.789971345339037,
                        "windSpeed": 1.504883253973103,
                        "windGust": 2.164240572186979,
                        "precipRate": 0.0,
                        "rainday": 0.0
        }
    }
    ]
}
