{
    "station":
    {
        "location": "Shefford, QC",
        "latitude": 45.2043,
        "longitude": -72.3529,
        "altitude (meters)": 300.0,
        "link": ""
    },
    "generation":
    {
        "time": "2024-08-06T10:15:00-0400",
        "generator": "weewx 5.1.0"
    },
    "current":
    {
        "temperature": {"value": 15.648989898989889, "units": "°C"},
        "dewpoint": {"value": 15.187003345955732, "units": "°C"},
        "humidity": {"value": 97.0909090909091, "units": "%"},
        "heat index": {"value": 15.80459595959596, "units": "°C"},
        "wind speed": {"value": 0.8773040764091774, "units": "km/h"},
        "wind gust": {"value": 2.6559991782973444, "units": "km/h"},
        "wind direction": {"value": 257.1710136029078, "units": "°"},
        "wind chill": {"value": 15.648989898989889, "units": "°C"},
        "rain rate": {"value": 0.0, "units": "cm/h"},
        "void_end": null
    },
    "day":
    {
        "max temperature": {"value": 15.999999999999998, "units": "°C", "at": "10:08:29 AM"},
        "min temperature": {"value": 12.277777777777775, "units": "°C", "at": "03:50:00 AM"},
        "max dewpoint": {"value": 15.52332622802849, "units": "°C", "at": "10:08:29 AM"},
        "min dewpoint": {"value": 12.12488176883462, "units": "°C", "at": "03:35:59 AM"},
        "max humidity": {"value": 99.0, "units": "%", "at": "12:00:03 AM"},
        "min humidity": {"value": 95.0, "units": "%", "at": "10:02:14 AM"},
        "max wind speed": {"value": 1.6048661701594378, "units": "km/h", "at": "09:35:00 AM"},
        "max wind gust": {"value": 4.310998666280064, "units": "km/h", "at": "12:40:00 AM"},
        "max rain rate": {"value": 0.0, "units": "cm/h", "at": "12:00:03 AM"},
        "rain total": {"value": 0.0, "units": "cm"},
        "void_end": null
    },
    "week":
    {
        "max temperature": {"value": 30.38888888888889, "units": "°C", "at": "01:05:22 PM (Sunday)"},
        "min temperature": {"value": 12.277777777777775, "units": "°C", "at": "03:50:00 AM (Tuesday)"},
        "max dewpoint": {"value": 23.50872237316893, "units": "°C", "at": "12:32:14 PM (Sunday)"},
        "min dewpoint": {"value": 12.12488176883462, "units": "°C", "at": "03:35:59 AM (Tuesday)"},
        "max humidity": {"value": 99.0, "units": "%", "at": "12:00:03 AM (Sunday)"},
        "min humidity": {"value": 63.0, "units": "%", "at": "01:14:07 PM (Sunday)"},
        "max wind speed": {"value": 6.738088824487294, "units": "km/h", "at": "08:20:00 PM (Monday)"},
        "max wind gust": {"value": 16.727994824758273, "units": "km/h", "at": "08:10:00 PM (Monday)"},
        "max rain rate": {"value": 0.7112000000000015, "units": "cm/h", "at": "09:10:00 PM (Sunday)"},
        "rain total": {"value": 1.3461999999999996, "units": "cm"},
        "void_end": null
    },
    "month":
    {
        "max temperature": {"value": 31.999999999999996, "units": "°C", "at": "2024-08-02 11:51:56 AM"},
        "min temperature": {"value": 12.277777777777775, "units": "°C", "at": "2024-08-06 03:50:00 AM"},
        "max dewpoint": {"value": 23.799731996181634, "units": "°C", "at": "2024-08-02 02:10:04 PM"},
        "min dewpoint": {"value": 12.12488176883462, "units": "°C", "at": "2024-08-06 03:35:59 AM"},
        "max humidity": {"value": 99.0, "units": "%", "at": "2024-08-01 12:00:05 AM"},
        "min humidity": {"value": 55.0, "units": "%", "at": "2024-08-02 12:48:11 PM"},
        "max wind speed": {"value": 6.738088824487294, "units": "km/h", "at": "2024-08-05 08:20:00 PM"},
        "max wind gust": {"value": 16.727994824758273, "units": "km/h", "at": "2024-08-05 08:10:00 PM"},
        "max rain rate": {"value": 7.0104, "units": "cm/h", "at": "2024-08-01 05:34:08 PM"},
        "rain total": {"value": 4.6228, "units": "cm"},
        "void_end": null
    },
    "year":
    {
        "max temperature": {"value": 31.999999999999996, "units": "°C", "at": "2024-08-02 11:51:56 AM"},
        "min temperature": {"value": 12.277777777777775, "units": "°C", "at": "2024-08-06 03:50:00 AM"},
        "max dewpoint": {"value": 23.799731996181634, "units": "°C", "at": "2024-08-02 02:10:04 PM"},
        "min dewpoint": {"value": 9.285956745026379, "units": "°C", "at": "2024-07-27 03:14:29 AM"},
        "max humidity": {"value": 99.0, "units": "%", "at": "2024-07-31 05:24:27 PM"},
        "min humidity": {"value": 49.0, "units": "%", "at": "2024-07-27 01:36:51 PM"},
        "max wind speed": {"value": 6.738088824487294, "units": "km/h", "at": "2024-08-05 08:20:00 PM"},
        "max wind gust": {"value": 16.727994824758273, "units": "km/h", "at": "2024-08-05 08:10:00 PM"},
        "max rain rate": {"value": 7.0104, "units": "cm/h", "at": "2024-08-01 05:34:08 PM"},
        "rain total": {"value": 5.791200000000001, "units": "cm"},
        "void_end": null
    }
}